Metadata-Version: 1.0
Name: titus
Version: 0.8.4
Summary: Python implementation of Portable Format for Analytics (PFA): producer, converter, and consumer.
Home-page: UNKNOWN
Author: Open Data Group
Author-email: support@opendatagroup.com
License: UNKNOWN
Platform: UNKNOWN
